{
    "https://www.youtube.com/watch?v=lPVBrRd9wCo": "Nto - Trauma (Worakls Remix).mp4",
    "https://www.youtube.com/watch?v=7eZIbmq5Jiw": "[Electro House] Virtual Riot - Energy Drink.mp4",
    "https://www.youtube.com/watch?v=BejgJThwuLw": "OVERWERK - 01 - The Nth \u00ba.mp4",
    "https://www.youtube.com/watch?v=zXX0Sa0Zn-k": "OVERWERK - 02 - Alive.mp4",
    "https://www.youtube.com/watch?v=x6-n6sMhL3I": "OVERWERK - 04 - Buzzin.mp4",
    "https://www.youtube.com/watch?v=JRneiRumUDo": "OVERWERK - 06 - Contact.mp4",
    "https://www.youtube.com/watch?v=YS4fXhiVEQM": "AWOLNATION - Sail (Unlimited Gravity Remix) (Audio).mp4",
    "https://www.youtube.com/watch?v=rk6cod9BJzw": "Crypt of the NecroDancer OST - Zone 1 Level 2.mp4",
    "https://www.youtube.com/watch?v=uV8ZqWwyYzQ": "Miley Cyrus - FU ft French Montana (Audio).mp4",
    "https://www.youtube.com/watch?v=0KSOMA3QBU0": "Katy Perry - Dark Horse (Official) ft Juicy J.mp4",
    "https://www.youtube.com/watch?v=QZYbRe9taiw": "The Basement Collection - AVGM - Blooba Doop Scooba.mp4",
    "https://www.youtube.com/watch?v=GmFlsVUCBc4": "The Binding of Isaac Wrath of the Lamb - Tomes.mp4",
    "https://www.youtube.com/watch?v=3AyXvWfQfYQ": "The Binding Of Isaac OST-Repentant.mp4",
    "https://www.youtube.com/watch?v=6EtG3tbTR60": "soundodger+ - Kirkhope - Danny Baranowsky.mp4",
    "https://www.youtube.com/watch?v=i6OtF7daIPM": "28 Weeks Later & 28 Days Later theme song by John Murphy.mp4",
    "https://www.youtube.com/watch?v=fiore9Z5iUg": "Lilly Wood & The Prick and Robin Schulz - Prayer In C (Robin Schulz Remix) (Official).mp4",
    "https://www.youtube.com/watch?v=EsKHlSmv2q8": "Den Svenska Bj\u00f6rnstammen - Svalkar vinden.mp4",
    "https://www.youtube.com/watch?v=qilVFJlt_PE": "Life Express - Wistful Idiot (Original Mix) [Bonerizing Records].mp4",
    "https://www.youtube.com/watch?v=ksme1nbbTAc": "Nightcore - Thrift Shop.mp4",
    "https://www.youtube.com/watch?v=iWJ9NY09cvQ": "Nightcore - Thrift Shop.mp4",
    "https://www.youtube.com/watch?v=q_gfD3nvh-8": "Girls Generation \uc18c\ub140\uc2dc\ub300 Run Devil Run MV.mp4",
    "https://www.youtube.com/watch?v=B2m_WnXjqnM": "What So Not - High You Are (Branchez Remix).mp4",
    "https://www.youtube.com/watch?v=TvbpQx-dQfQ": "Vanic x Zella Day - Hypnotic.mp4",
    "https://www.youtube.com/watch?v=W9P_qUnMaFg": "Dynoro & Gigi D\u2019Agostino - In My Mind.mp4",
    "https://www.youtube.com/watch?v=tKvqhlhXq9s": "[SONG VERSION] IM A DUDE RDJ Tropic Thunder Remix.mp4",
    "https://www.youtube.com/watch?v=HyYcYBhRs8Y": "Nooran sisters - What if the Nooran sisters was a club song (tiktok@itsdiorange).mp4",
    "https://www.youtube.com/watch?v=AlLid7sY4NE": "Morena Mariana Nolasco part Vitor Kley.mp4",
    "https://www.youtube.com/watch?v=nBphGQqqQTU": "Rogue Legacy OST - [19] Trilobyte (Castle) [Game Version].mp4",
    "https://www.youtube.com/watch?v=fRu8Joqo8VA": "Rogue Legacy OST - [11] Narwhal (Maya  Tower).mp4",
    "https://www.youtube.com/watch?v=uuu7dTEPLs8": "Rogue Legacy OST - [15] Whale Shark (End Sequence).mp4",
    "https://www.youtube.com/watch?v=lYNvwErDg4c": "Rogue Legacy OST - [18] Whale Shark (End Sequence Sad Version).mp4",
    "https://www.youtube.com/watch?v=-_U7ooCM5yk": "Whale Shark (Rogue Legacy 2 Version).mp4",
    "https://www.youtube.com/watch?v=bex9bA7oQwA": "Zella Day - East of Eden (Official Audio).mp4",
    "https://www.youtube.com/watch?v=BCnJAMkETiU": "\u3010Electro\u3011OVERWERK - Toccata.mp4",
    "https://www.youtube.com/watch?v=JnIKLRA31nw": "OVERWERK - Daybreak.mp4",
    "https://www.youtube.com/watch?v=JaAWdljhD5o": "SAIL - AWOLNATION (Unofficial Video).mp4",
    "https://www.youtube.com/watch?v=PDJLvF1dUek": "Caramella Girls - Caramelldansen HD Version (Swedish Original).mp4",
    "https://www.youtube.com/watch?v=UbQgXeY_zi4": "Caravan Palace - Lone Digger (Official MV).mp4",
    "https://www.youtube.com/watch?v=FHccClTAdzc": "CAZZETTE - She Wants Me Dead ft The High (CAZZETTE vs AronChupa) [Official Video].mp4",
    "https://www.youtube.com/watch?v=eS_korRhTDk": "Lemaitre - Closer ft Jennie A (UK Version).mp4",
    "https://www.youtube.com/watch?v=TApuJW7cuiI": "Dance Monkey - AMV - \u300cAnime MV\u300d.mp4",
    "https://www.youtube.com/watch?v=VFZNvj-HfBU": "Da\u00f0i Freyr (Da\u00f0i & Gagnamagni\u00f0) \u2013 Think About Things (Official Video).mp4",
    "https://www.youtube.com/watch?v=k1BneeJTDcU": "Welcome to the Internet - Bo Burnham (from Inside -- ALBUM OUT NOW).mp4",
    "https://www.youtube.com/watch?v=lX44CAz-JhU": "SIAM\u00c9S The Wolf [Official Animated Music Video].mp4",
    "https://www.youtube.com/watch?v=vSkb0kDacjs": "Woodkid - Iron (Official Video).mp4",
    "https://www.youtube.com/watch?v=t-VbAZcyZ_U": "[Eng CC] Soviet March - 1980s Soviet Army [Red Alert 3].mp4",
    "https://www.youtube.com/watch?v=zZsEVXYTbtw": "Nooran Sisters - Patakha guddi (Diorange Remix Nurik Extended).mp4",
    "https://www.youtube.com/watch?v=mj-v6zCnEaw": "NOMA - Brain Power.mp4",
    "https://www.youtube.com/watch?v=cFKgxL9F1BM": "Exist.mp4",
    "https://www.youtube.com/watch?v=ZAcDOuPxMyQ": "Vanic x KFlay - Cant Sleep.mp4",
    "https://www.youtube.com/watch?v=TbsBEb1ZxWA": "Caravan Palace - Lone Digger (Album version).mp4",
    "https://www.youtube.com/watch?v=52Gg9CqhbP8": "Stuck In the Sound - Lets Go [Official Video].mp4",
    "https://www.youtube.com/watch?v=ymNFyxvIdaM": "Bomfunk MCs - Freestyler (Video Original Version).mp4",
    "https://www.youtube.com/watch?v=_lK4cX5xGiQ": "Tenacious D - Tribute (Official Video).mp4",
    "https://www.youtube.com/watch?v=xat1GVnl8-k": "Bloodhound Gang - The Bad Touch (Official Video).mp4",
    "https://www.youtube.com/watch?v=89tgpzE4qkY": "Bloodhound Gang - Uhn Tiss Uhn Tiss Uhn Tiss (Explicit) [Official Video].mp4",
    "https://www.youtube.com/watch?v=JZpxaiNV_sM": "Bloodhound Gang - Foxtrot Uniform Charlie Kilo (Official Video).mp4",
    "https://www.youtube.com/watch?v=If9fC9aJd-U": "Bloodhound Gang - The Ballad Of Chasey Lain.mp4",
    "https://www.youtube.com/watch?v=m0VIJTMsRc4": "Bloodhound Gang Along Comes Mary.mp4",
    "https://www.youtube.com/watch?v=wnDCmUd8xDs": "The Inevitable Return Of The Great White Dope.mp4",
    "https://www.youtube.com/watch?v=uLF6VFME2jc": "01 Frostpunk Theme - Frostpunk Original Soundtrack.mp4",
    "https://www.youtube.com/watch?v=GdzrrWA8e7A": "Zelda & Chill.mp4",
    "https://www.youtube.com/watch?v=qbk9Aj-QkhY": "Ellie Goulding - Lights (Nitti Gritti Remix).mp4",
    "https://www.youtube.com/watch?v=Imixg3jrJS8": "Ellie Goulding - Lights (Bassnectar Remix  Official Video).mp4",
    "https://www.youtube.com/watch?v=nGlIDlOqurA": "Ellie Goulding - Lights (Bassnectar Remix) [FULL OFFICIAL].mp4",
    "https://www.youtube.com/watch?v=zP50Ewh31E4": "Alex Clare - Too Close.mp4",
    "https://www.youtube.com/watch?v=Ayi2CJU2xmQ": "Dumbbell Nan Kilo Moteru Opening\u300cOnegai Muscle\u300dFull Version.mp4",
    "https://www.youtube.com/watch?v=MlK1mbeeCcE": "Im Yours [Lofi Fruits Release].mp4"
}